sbmlsh/__init__.py
sbmlsh/mod2sbml.py
sbmlsh/roundtrip.py
sbmlsh/sbml-latex-extract.py
sbmlsh/sbml2latex.py
sbmlsh/sbml2mod.py
sbmlsh-0.0.4.dist-info/METADATA
sbmlsh-0.0.4.dist-info/WHEEL
sbmlsh-0.0.4.dist-info/entry_points.txt
sbmlsh-0.0.4.dist-info/licenses/LICENSE
sbmlsh-0.0.4.dist-info/RECORD
