Metadata-Version: 2.4
Name: sbmlsh
Version: 0.0.4
Summary: SBML-shorthand conversion tools
Project-URL: Homepage, https://github.com/darrenjw/sbml-sh
Project-URL: Documentation, https://sbml-sh.readthedocs.io/
Project-URL: Issues, https://github.com/darrenjw/sbml-sh/issues
Author-email: Darren Wilkinson <darrenjwilkinson@btinternet.com>
License-File: LICENSE
Classifier: License :: OSI Approved :: Apache Software License
Classifier: Operating System :: OS Independent
Classifier: Programming Language :: Python :: 3
Requires-Python: >=3.8
Requires-Dist: python-libsbml
